kwok.cpython-39-x86_64-linux-gnu.so
kwok-1.1.7.dist-info/METADATA
kwok-1.1.7.dist-info/WHEEL
kwok-1.1.7.dist-info/top_level.txt
kwok-1.1.7.dist-info/RECORD
