Metadata-Version: 2.1
Name: kwok
Version: 1.1.7
Summary: A fast maximum weight bipartite matching algorithm from 'A Faster Algorithm for Maximum Weight Matching on Unrestricted Bipartite Graphs'
Home-page: https://github.com/aimidi/kwok
Author: Shawxing Kwok
Author-email: shawxingkwok@126.com
License: UNKNOWN
Platform: UNKNOWN
Classifier: Development Status :: 4 - Beta
Classifier: Intended Audience :: Science/Research
Classifier: Intended Audience :: Developers
Classifier: License :: OSI Approved :: MIT License
Classifier: Programming Language :: Python :: 3.6
Classifier: Programming Language :: Python :: 3.7
Classifier: Programming Language :: Python :: 3.8
Classifier: Programming Language :: Python :: 3.9
Classifier: Programming Language :: Python :: 3.10
Classifier: Programming Language :: Python :: 3.11
Classifier: Programming Language :: Python :: 3.12
Classifier: Programming Language :: Python :: 3.13
Classifier: Programming Language :: C++
Classifier: Operating System :: OS Independent
Requires-Python: >=3.6
